org2ical/__init__.py
org2ical-0.0.4.dist-info/LICENSE
org2ical-0.0.4.dist-info/METADATA
org2ical-0.0.4.dist-info/WHEEL
org2ical-0.0.4.dist-info/top_level.txt
org2ical-0.0.4.dist-info/RECORD
