Metadata-Version: 2.1
Name: org2ical
Version: 0.0.4
Summary: Generate a iCalendar (.ics) file based on a OrgMode (.org) file.
Home-page: https://github.com/j3soon/org2ical
Author: Johnson
Author-email: j3.soon777@gmail.com
Project-URL: Issues, https://github.com/j3soon/org2ical/issues
Project-URL: Source Code, https://github.com/j3soon/org2ical
Keywords: package,parser,converter,python,orgmode,icalendar
Classifier: Development Status :: 4 - Beta
Classifier: Intended Audience :: Developers
Classifier: Programming Language :: Python :: 3.7
Classifier: Programming Language :: Python :: 3.8
Classifier: Programming Language :: Python :: 3.9
Classifier: Programming Language :: Python :: 3.10
Classifier: License :: OSI Approved :: MIT License
Classifier: Operating System :: OS Independent
License-File: LICENSE
Requires-Dist: orgparse >=0.3.2
Provides-Extra: testing
Requires-Dist: pytest ; extra == 'testing'
Requires-Dist: mypy ; extra == 'testing'
Requires-Dist: flake8 ; extra == 'testing'
Requires-Dist: pylint ; extra == 'testing'
Requires-Dist: icalendar ; extra == 'testing'
Requires-Dist: python-dateutil ; extra == 'testing'
